ollamadiffuser/__init__.py
ollamadiffuser/__main__.py
ollamadiffuser/api/__init__.py
ollamadiffuser/api/server.py
ollamadiffuser/cli/__init__.py
ollamadiffuser/cli/commands.py
ollamadiffuser/cli/main.py
ollamadiffuser/core/__init__.py
ollamadiffuser/core/config/__init__.py
ollamadiffuser/core/config/model_registry.py
ollamadiffuser/core/config/settings.py
ollamadiffuser/core/inference/__init__.py
ollamadiffuser/core/inference/engine.py
ollamadiffuser/core/models/__init__.py
ollamadiffuser/core/models/gguf_loader.py
ollamadiffuser/core/models/manager.py
ollamadiffuser/core/models/registry.py
ollamadiffuser/core/utils/__init__.py
ollamadiffuser/core/utils/controlnet_preprocessors.py
ollamadiffuser/core/utils/download_utils.py
ollamadiffuser/core/utils/lora_manager.py
ollamadiffuser/ui/__init__.py
ollamadiffuser/ui/web.py
ollamadiffuser/ui/samples/.DS_Store
ollamadiffuser/ui/samples/metadata.json
ollamadiffuser/ui/samples/canny/geometric_shapes.png
ollamadiffuser/ui/samples/canny/house_outline.png
ollamadiffuser/ui/samples/canny/portrait_outline.png
ollamadiffuser/ui/samples/depth/linear_perspective.png
ollamadiffuser/ui/samples/depth/radial_gradient.png
ollamadiffuser/ui/samples/depth/sphere_3d.png
ollamadiffuser/ui/samples/openpose/running_pose.png
ollamadiffuser/ui/samples/openpose/sitting_pose.png
ollamadiffuser/ui/samples/openpose/standing_pose.png
ollamadiffuser/ui/samples/scribble/car_sketch.png
ollamadiffuser/ui/samples/scribble/face_sketch.png
ollamadiffuser/ui/samples/scribble/tree_sketch.png
ollamadiffuser/ui/templates/index.html
ollamadiffuser/utils/__init__.py
ollamadiffuser-1.2.3.dist-info/licenses/LICENSE
ollamadiffuser-1.2.3.dist-info/METADATA
ollamadiffuser-1.2.3.dist-info/WHEEL
ollamadiffuser-1.2.3.dist-info/entry_points.txt
ollamadiffuser-1.2.3.dist-info/top_level.txt
ollamadiffuser-1.2.3.dist-info/RECORD
