Metadata-Version: 2.4
Name: ollamadiffuser
Version: 1.2.3
Summary: 🎨 Local AI Image Generation with Ollama-style CLI for Stable Diffusion, FLUX.1, and LoRA support
Home-page: https://github.com/ollamadiffuser/ollamadiffuser
Author: OllamaDiffuser Team
Author-email: OllamaDiffuser Team <ollamadiffuser@gmail.com>
License: MIT
Project-URL: Homepage, https://www.ollamadiffuser.com/
Project-URL: Website, https://www.ollamadiffuser.com/
Project-URL: Repository, https://github.com/ollamadiffuser/ollamadiffuser
Project-URL: Issues, https://github.com/ollamadiffuser/ollamadiffuser/issues
Project-URL: Documentation, https://www.ollamadiffuser.com/
Project-URL: Bug Reports, https://github.com/ollamadiffuser/ollamadiffuser/issues
Project-URL: Feature Requests, https://github.com/ollamadiffuser/ollamadiffuser/issues
Project-URL: Source Code, https://github.com/ollamadiffuser/ollamadiffuser
Keywords: diffusion,image-generation,ai,machine-learning,lora,ollama,stable-diffusion,flux,local-ai,controlnet,web-ui,cli
Classifier: Development Status :: 4 - Beta
Classifier: Intended Audience :: Developers
Classifier: Intended Audience :: End Users/Desktop
Classifier: License :: OSI Approved :: MIT License
Classifier: Operating System :: OS Independent
Classifier: Programming Language :: Python :: 3
Classifier: Programming Language :: Python :: 3.10
Classifier: Programming Language :: Python :: 3.11
Classifier: Programming Language :: Python :: 3.12
Classifier: Programming Language :: Python :: 3.13
Classifier: Topic :: Scientific/Engineering :: Artificial Intelligence
Classifier: Topic :: Multimedia :: Graphics
Classifier: Topic :: Software Development :: Libraries :: Python Modules
Classifier: Environment :: Console
Classifier: Environment :: Web Environment
Requires-Python: >=3.10
License-File: LICENSE
Requires-Dist: torch>=2.1.0
Requires-Dist: diffusers>=0.26.0
Requires-Dist: transformers>=4.35.0
Requires-Dist: accelerate>=0.25.0
Requires-Dist: fastapi>=0.104.0
Requires-Dist: uvicorn>=0.23.0
Requires-Dist: huggingface-hub>=0.16.0
Requires-Dist: Pillow>=9.0.0
Requires-Dist: click>=8.0.0
Requires-Dist: rich>=13.0.0
Requires-Dist: pydantic>=2.0.0
Requires-Dist: protobuf>=3.20.0
Requires-Dist: sentencepiece>=0.1.99
Requires-Dist: safetensors>=0.3.0
Requires-Dist: python-multipart>=0.0.0
Requires-Dist: psutil>=5.9.0
Requires-Dist: jinja2>=3.0.0
Requires-Dist: peft>=0.10.0
Requires-Dist: numpy>=1.21.0
Requires-Dist: controlnet-aux>=0.0.7
Requires-Dist: opencv-python>=4.8.0
Requires-Dist: stable-diffusion-cpp-python>=0.1.0
Requires-Dist: gguf>=0.1.0
Provides-Extra: dev
Requires-Dist: pytest>=7.0.0; extra == "dev"
Requires-Dist: pytest-asyncio>=0.21.0; extra == "dev"
Requires-Dist: black>=23.0.0; extra == "dev"
Requires-Dist: isort>=5.12.0; extra == "dev"
Requires-Dist: flake8>=6.0.0; extra == "dev"
Dynamic: author
Dynamic: home-page
Dynamic: license-file
Dynamic: requires-python
